pip_preserve/__init__.py
pip_preserve/__main__.py
pip_preserve/_lib.py
pip_preserve/cli.py
pip_preserve-0.0.2.post1.dist-info/entry_points.txt
pip_preserve-0.0.2.post1.dist-info/LICENSE
pip_preserve-0.0.2.post1.dist-info/WHEEL
pip_preserve-0.0.2.post1.dist-info/METADATA
pip_preserve-0.0.2.post1.dist-info/RECORD
