Metadata-Version: 2.1
Name: pip-preserve
Version: 0.0.2.post1
Summary: Output installed Python packages in requirements format, including also hashes of Python packages.
Keywords: packaging,pip,dependencies,requirements
Author-email: Fridolin Pokorny <fridolin.pokorny@gmail.com>
Maintainer-email: Fridolin Pokorny <fridolin.pokorny@gmail.com>
Requires-Python: >3.6
Classifier: License :: OSI Approved :: MIT License
Requires-Dist: click
Requires-Dist: daiquiri
Requires-Dist: packaging
Requires-Dist: pytest ; extra == "test"
Project-URL: Documentation, https://github.com/fridex/pip-preserve
Project-URL: Home, https://pypi.org/project/pip-preserve/
Project-URL: Issue, https://github.com/fridex/pip-preserve/issues
Project-URL: Source, https://github.com/fridex/pip-preserve
Provides-Extra: test
